dgp/__init__.py
dgp/__main__.py
dgp/dataset_to_proben1.py
dgp/dgp_logger.py
dgp/proben.py
dgp/settings.py
dgp/utils.py
dgp/datasets/proben1/cancer1.trn
dgp/datasets/proben1/cancer1.tst
dgp/datasets/proben1/cancer1.val
dgp/datasets/proben1/cancer2.trn
dgp/datasets/proben1/cancer2.tst
dgp/datasets/proben1/cancer2.val
dgp/datasets/proben1/cancer3.trn
dgp/datasets/proben1/cancer3.tst
dgp/datasets/proben1/cancer3.val
dgp/datasets/proben1/g.trn
dgp/datasets/proben1/g.tst
dgp/datasets/proben1/g.val
dgp/datasets/proben1/minih.trn
dgp/datasets/proben1/minih.tst
dgp/datasets/proben1/minih.val
dgp/datasets/proben1/miniheli.txt
dgp/datasets/proben1/spambase.DOCUMENTATION
dgp/datasets/proben1/spambase.csv
dgp/datasets/proben1/spambase.names
dgp/datasets/proben1/spambase1.trn
dgp/datasets/proben1/spambase1.tst
dgp/datasets/proben1/spambase1.val
dgp/datasets/proben1/spambase2.trn
dgp/datasets/proben1/spambase2.tst
dgp/datasets/proben1/spambase2.val
dgp/datasets/proben1/spambase3.trn
dgp/datasets/proben1/spambase3.tst
dgp/datasets/proben1/spambase3.val
dgp/ga_optimizer/__init__.py
dgp/ga_optimizer/toolbox.py
dgp/ga_optimizer/types.py
dgp/ga_optimizer/utils.py
tests/__init__.py
tests/test__main__.py
tests/test_dataset_to_proben1.py
tests/test_deep_g_prop.py
tests/test_dgp_logger.py
tests/test_ga_optimizer.py
tests/test_utils.py
tests/ga_optimizer/__init__.py
tests/ga_optimizer/test__init__.py
tests/ga_optimizer/test_types.py
tests/ga_optimizer/test_utils.py
DeepGProp-1.0.8.dist-info/LICENSE
DeepGProp-1.0.8.dist-info/METADATA
DeepGProp-1.0.8.dist-info/WHEEL
DeepGProp-1.0.8.dist-info/entry_points.txt
DeepGProp-1.0.8.dist-info/top_level.txt
DeepGProp-1.0.8.dist-info/RECORD
