Metadata-Version: 2.1
Name: DeepGProp
Version: 1.0.8
Summary: Train Multilayer Perceptrons with Genetic Algorithms.
Home-page: https://github.com/lulivi/dgp-lib
Author: Luis Liñán
Author-email: luislivilla@gmail.com
License: GPLv3
Download-URL: https://github.com/lulivi/dgp-lib/releases/tag/v1.0.8
Platform: UNKNOWN
Classifier: License :: OSI Approved :: GNU General Public License v3 (GPLv3)
Classifier: Operating System :: POSIX :: Linux
Classifier: Development Status :: 4 - Beta
Classifier: Programming Language :: Python :: 3.6
Classifier: Programming Language :: Python :: 3.7
Classifier: Intended Audience :: Education
Classifier: Intended Audience :: Science/Research
Classifier: Topic :: Scientific/Engineering :: Artificial Intelligence
Classifier: Programming Language :: Python :: 3.8
Requires-Python: >=3.6,<3.9
Requires-Dist: tensorflow
Requires-Dist: numpy (>=1.18.2)
Requires-Dist: pandas (>=1.0.3)
Requires-Dist: deap (>=1.3.1)
Requires-Dist: scikit-learn (>=0.22.2.post1)
Requires-Dist: Theano-PyMC (==1.0.10)
Requires-Dist: Keras (==2.3.1)
Requires-Dist: click (==7.1.2)
Requires-Dist: tabulate (==0.8.7)
